archon/__init__.py
archon/app.py
archon/controller.py
archon/exceptions.py
archon/hub.py
archon/models.py
archon/router.py
archon/test.py
archon-0.3.3.dist-info/DESCRIPTION.rst
archon-0.3.3.dist-info/METADATA
archon-0.3.3.dist-info/RECORD
archon-0.3.3.dist-info/WHEEL
archon-0.3.3.dist-info/metadata.json
archon-0.3.3.dist-info/top_level.txt
tests/__init__.py
tests/test_auth.py
tests/test_base.py
tests/test_controller.py
tests/test_delete.py
tests/test_http.py
tests/test_parse.py
tests/test_save.py
tests/test_subscribe.py
tests/test_unsubscribe.py
tests/test_update.py
tests/testapp/__init__.py
tests/testapp/app.py
tests/testapp/models/__init__.py
tests/testapp/models/company.py
tests/testapp/models/employee.py
