Metadata-Version: 2.0
Name: archon
Version: 0.3.3
Summary: A framework for websocket APIs.
Home-page: https://github.com/JasperStam/archon
Author: Jasper Stam
Author-email: jasper@strnk.nl
License: MIT
Keywords: flask sqlalchemy websocket api pubsub
Platform: UNKNOWN
Classifier: Development Status :: 3 - Alpha
Classifier: Environment :: Web Environment
Classifier: Intended Audience :: Developers
Classifier: License :: OSI Approved :: MIT License
Classifier: Operating System :: OS Independent
Classifier: Programming Language :: Python :: 3
Classifier: Programming Language :: Python :: 3.3
Classifier: Programming Language :: Python :: 3.4
Classifier: Programming Language :: Python :: 3.5
Classifier: Programming Language :: Python :: 3.6
Classifier: Topic :: Internet :: WWW/HTTP :: Dynamic Content
Classifier: Topic :: Software Development :: Libraries :: Python Modules
Requires-Dist: Flask (>=0.12.0)
Requires-Dist: Flask-Migrate (>=2.0.3)
Requires-Dist: Flask-SQLAlchemy (>=2.1)
Requires-Dist: Flask-Script (>=2.0.5)
Requires-Dist: Flask-Sockets (>=0.2.1)
Requires-Dist: gevent (>=1.1.2)
Requires-Dist: greenlet (>=0.4.12)
Requires-Dist: pyjwt (>=1.4.2)
Requires-Dist: python-dateutil (>=2.6.0)
Requires-Dist: python-dotenv (>=0.6.3)
Requires-Dist: requests (>=2.13.0)
